{
  "updated": "2026-06-26T16:11:09Z",
  "data": {
    "2330.TW": {
      "price": 2340.0,
      "change": -170.0,
      "pct": -6.77,
      "prev": 2510.0,
      "currency": "TWD",
      "state": "CLOSED",
      "name": "台積電"
    },
    "2454.TW": {
      "price": 3880.0,
      "change": -585.0,
      "pct": -13.1,
      "prev": 4465.0,
      "currency": "TWD",
      "state": "CLOSED",
      "name": "聯發科"
    },
    "2317.TW": {
      "price": 248.5,
      "change": -20.0,
      "pct": -7.45,
      "prev": 268.5,
      "currency": "TWD",
      "state": "CLOSED",
      "name": "鴻海"
    },
    "0050.TW": {
      "price": 103.1,
      "change": -8.05,
      "pct": -7.24,
      "prev": 111.15,
      "currency": "TWD",
      "state": "CLOSED",
      "name": "元大台灣50"
    },
    "0056.TW": {
      "price": 51.45,
      "change": -2.6,
      "pct": -4.81,
      "prev": 54.05,
      "currency": "TWD",
      "state": "CLOSED",
      "name": "元大高股息"
    },
    "NVDA": {
      "price": 194.03,
      "change": -16.66,
      "pct": -7.9,
      "prev": 210.69,
      "currency": "USD",
      "state": "CLOSED",
      "name": "輝達"
    },
    "AAPL": {
      "price": 275.75,
      "change": -22.26,
      "pct": -7.47,
      "prev": 298.01,
      "currency": "USD",
      "state": "CLOSED",
      "name": "蘋果"
    },
    "MSFT": {
      "price": 367.86,
      "change": -11.54,
      "pct": -3.04,
      "prev": 379.4,
      "currency": "USD",
      "state": "CLOSED",
      "name": "微軟"
    },
    "VOO": {
      "price": 674.84,
      "change": -13.27,
      "pct": -1.93,
      "prev": 688.11,
      "currency": "USD",
      "state": "CLOSED",
      "name": "Vanguard S&P500"
    },
    "QQQ": {
      "price": 711.41,
      "change": -29.21,
      "pct": -3.94,
      "prev": 740.62,
      "currency": "USD",
      "state": "CLOSED",
      "name": "Invesco QQQ"
    }
  }
}