{
  "updated": "2026-06-12T05:48:14Z",
  "data": {
    "2330.TW": {
      "price": 2295.0,
      "change": 0.0,
      "pct": 0.0,
      "prev": 2295.0,
      "currency": "TWD",
      "state": "CLOSED",
      "name": "台積電"
    },
    "2454.TW": {
      "price": 4185.0,
      "change": 115.0,
      "pct": 2.83,
      "prev": 4070.0,
      "currency": "TWD",
      "state": "CLOSED",
      "name": "聯發科"
    },
    "2317.TW": {
      "price": 261.0,
      "change": -8.5,
      "pct": -3.15,
      "prev": 269.5,
      "currency": "TWD",
      "state": "CLOSED",
      "name": "鴻海"
    },
    "0050.TW": {
      "price": 101.9,
      "change": 0.95,
      "pct": 0.94,
      "prev": 100.95,
      "currency": "TWD",
      "state": "CLOSED",
      "name": "元大台灣50"
    },
    "0056.TW": {
      "price": 50.5,
      "change": 1.05,
      "pct": 2.12,
      "prev": 49.45,
      "currency": "TWD",
      "state": "CLOSED",
      "name": "元大高股息"
    },
    "NVDA": {
      "price": 204.87,
      "change": -13.79,
      "pct": -6.31,
      "prev": 218.66,
      "currency": "USD",
      "state": "CLOSED",
      "name": "輝達"
    },
    "AAPL": {
      "price": 295.63,
      "change": -15.6,
      "pct": -5.01,
      "prev": 311.23,
      "currency": "USD",
      "state": "CLOSED",
      "name": "蘋果"
    },
    "MSFT": {
      "price": 390.34,
      "change": -37.71,
      "pct": -8.81,
      "prev": 428.05,
      "currency": "USD",
      "state": "CLOSED",
      "name": "微軟"
    },
    "VOO": {
      "price": 678.23,
      "change": -17.83,
      "pct": -2.56,
      "prev": 696.06,
      "currency": "USD",
      "state": "CLOSED",
      "name": "Vanguard S&P500"
    },
    "QQQ": {
      "price": 717.12,
      "change": -23.49,
      "pct": -3.17,
      "prev": 740.61,
      "currency": "USD",
      "state": "CLOSED",
      "name": "Invesco QQQ"
    }
  }
}