{
  "updated": "2026-07-02T16:02:00Z",
  "data": {
    "2330.TW": {
      "price": 2465.0,
      "change": 125.0,
      "pct": 5.34,
      "prev": 2340.0,
      "currency": "TWD",
      "state": "CLOSED",
      "name": "台積電"
    },
    "2454.TW": {
      "price": 4345.0,
      "change": 465.0,
      "pct": 11.98,
      "prev": 3880.0,
      "currency": "TWD",
      "state": "CLOSED",
      "name": "聯發科"
    },
    "2317.TW": {
      "price": 239.0,
      "change": -9.5,
      "pct": -3.82,
      "prev": 248.5,
      "currency": "TWD",
      "state": "CLOSED",
      "name": "鴻海"
    },
    "0050.TW": {
      "price": 108.8,
      "change": 5.7,
      "pct": 5.53,
      "prev": 103.1,
      "currency": "TWD",
      "state": "CLOSED",
      "name": "元大台灣50"
    },
    "0056.TW": {
      "price": 52.6,
      "change": 1.15,
      "pct": 2.24,
      "prev": 51.45,
      "currency": "TWD",
      "state": "CLOSED",
      "name": "元大高股息"
    },
    "NVDA": {
      "price": 194.3,
      "change": -1.44,
      "pct": -0.74,
      "prev": 195.74,
      "currency": "USD",
      "state": "CLOSED",
      "name": "輝達"
    },
    "AAPL": {
      "price": 306.26,
      "change": 31.11,
      "pct": 11.31,
      "prev": 275.15,
      "currency": "USD",
      "state": "CLOSED",
      "name": "蘋果"
    },
    "MSFT": {
      "price": 389.05,
      "change": 36.22,
      "pct": 10.26,
      "prev": 352.83,
      "currency": "USD",
      "state": "CLOSED",
      "name": "微軟"
    },
    "VOO": {
      "price": 684.01,
      "change": 8.3,
      "pct": 1.23,
      "prev": 675.71,
      "currency": "USD",
      "state": "CLOSED",
      "name": "Vanguard S&P500"
    },
    "QQQ": {
      "price": 714.68,
      "change": -1.7,
      "pct": -0.24,
      "prev": 716.38,
      "currency": "USD",
      "state": "CLOSED",
      "name": "Invesco QQQ"
    }
  }
}