{
  "date": "2026-06-15",
  "market_shocks": [
    {
      "title": "費半暴跌10%！科技股拋售潮引發市場恐慌",
      "sources": [
        {
          "name": "今周刊",
          "url": "https://www.businesstoday.com.tw/article/category/183009/post/202606060002/"
        },
        {
          "name": "CMoney 股市爆料同學會",
          "url": "https://www.cmoney.tw/forum/article/178653291"
        }
      ],
      "summary": "美股於6月5日出現近年罕見的全面性拋售，費城半導體指數(SOX)暴跌10.26%，創2020年3月疫情以來最大單日跌幅。博通客製化AI芯片業務成長未達預期，引發資金大舉撤離。台指期夜盤創史上最大單日跌點3,006點。",
      "tw_stock_impact": "台積電ADR跌6.69%、輝達跌6.20%。台指期大跌3,006點，台股面臨拋售潮與槓杆平倉風險。法人現金水位偏低(3.9%)，市場流動性風險升高。",
      "investment_insight": "短期內迴避半導體超買風險，觀察台積電除息(6/11)與Fed決議(6/17)後的市場方向。資本市場過度擁擠，應留意獲利了結機會。",
      "title_idea": "費半暴跌為AI泡沫破滅前兆？台股急轉直下3000點背後的市場真相",
      "local_angle": "台積電位居全球芯片代工中心，為台股權重龍頭。費半跌幅直接衝擊台股表現，是台灣投資人關鍵觀察指標。"
    },
    {
      "title": "馬斯克成全球首位三兆富翁 SpaceX IPO點燃太空經濟新浪潮",
      "sources": [
        {
          "name": "Al Jazeera",
          "url": "https://www.aljazeera.com/economy/2026/6/12/spacex-ipo-debuts-in-us-markets-musk-becomes-worlds-first-trillionaire"
        },
        {
          "name": "Fortune",
          "url": "https://fortune.com/2026/06/12/elon-musk-wealth-double-south-africa-gdp/"
        }
      ],
      "summary": "SpaceX於6月12日在納斯達克上市，IPO募資750億美元(史上最大)，估值1.96兆美元，股價第二日上漲20%。馬斯克淨資產超過3兆美元，成為人類歷史上首位三兆富翁，其財富已超越南非全國GDP的2倍。",
      "tw_stock_impact": "Space X上市引發全球資金競逐，可能分流台股資金。但長期看，太空經濟成長將帶動台灣航太供應鏈與相關零組件廠商機會，包括精密加工、電子零件供應商。",
      "investment_insight": "太空經濟成為新興投資主軸。關注台灣航太產業鏈與衛星通訊相關廠商，以及為SpaceX供應關鍵零組件的代工廠商機遇。",
      "title_idea": "馬斯克成首位三兆富翁！SpaceX上市後股價狂漲20%，新太空時代投資大浪潮開始",
      "local_angle": "Business Today報導提及Space X上市對台股概念股的影響，台灣精密製造與航太供應鏈是間接受益者。"
    },
    {
      "title": "全球股市同步下跌 AI泡沫論成主流聲音",
      "sources": [
        {
          "name": "新浪財經",
          "url": "https://finance.sina.com.cn/jjxw/2026-06-06/doc-iniancxs7517241.shtml"
        },
        {
          "name": "聯合新聞網",
          "url": "https://udn.com/news/story/6837/9565159"
        }
      ],
      "summary": "美國5月非農數據超預期(17.2萬人)推升升息預期，加上市場對AI投資回報的質疑升溫，引發全球股市同步下跌。摩根士丹利、貝萊德等大型機構紛紛發聲，認為AI概念股估值過高，面臨泡沫風險。",
      "tw_stock_impact": "台股中AI相關題材股(如AI晶片、伺服器散熱等)面臨估值修正壓力。科技股權重高達40%以上，直接衝擊台股指數與投資人投資組合。",
      "investment_insight": "警惕AI板塊高估值風險。尋找基本面扎實、真實營收成長的AI受惠股，迴避純概念性的投機標的。觀察Fed決議與非農數據作為轉折點。",
      "title_idea": "AI泡沫論大爆發！美股科技股市值蒸發1.3兆、台股權重股面臨修正風險",
      "local_angle": "台灣科技產業(特別是台積電、台達電)高度仰賴海外市場，全球股市震盪直接威脅台灣企業獲利前景。"
    },
    {
      "title": "Michael Burry預警市場似1999年科網泡沫 加倍阿里巴巴持股",
      "sources": [
        {
          "name": "CNBC",
          "url": "https://www.cnbc.com/2026/05/08/michael-burry-says-the-market-today-feels-like-the-last-months-of-the-1999-2000-bubble.html"
        },
        {
          "name": "Yahoo Finance",
          "url": "https://finance.yahoo.com/markets/stocks/articles/michael-burry-boosts-alibaba-stake-072903974.html"
        }
      ],
      "summary": "著名對沖基金經理人Michael Burry發表報告《The Heretic's Guide to AI's Stars Part III》，警告市場環境與1999-2000年科網泡沫末期相似。同時他加倍阿里巴巴持股，於111.90美元位置增持，並表示「時機來臨時，股票將迅速飆升」。",
      "tw_stock_impact": "顯示市場存在極端不確定性。台灣科技股(尤其是AI相關股)可能面臨與海外同步調整的風險。但Michael Burry的逆向操作也提示：下跌可能孕育長期機會。",
      "investment_insight": "短期謹慎，中期布局。當市場恐慌時，購買質地優良、被過度拋售的優質公司。Michael Burry的阿里巴巴加持動作值得參考：尋找被低估的成長型標的。",
      "title_idea": "『大空頭』Michael Burry重磅預警：這次比科網泡沫還危險，但他卻加倍買這檔股票",
      "local_angle": "Michael Burry是全球頂級對沖基金經理人，其見解對台灣投資人具參考價值。他看空AI、看好中概股的策略，反映出市場的極端分化與機會。"
    }
  ],
  "investment_opportunities": [
    {
      "title": "台積電配息7元創新高 AI需求年增70%保證長期成長",
      "sources": [
        {
          "name": "豐雲學堂",
          "url": "https://www.sinotrade.com.tw/richclub/hotstock/2026%E5%8F%B0%E7%A9%8D%E9%9B%BB%E4%BD%95%E6%99%82%E9%99%A4%E6%81%AF-%E6%9C%AC%E6%AC%A1%E9%85%8D%E7%99%BC6%E5%85%83%E7%8F%BE%E9%87%91%E8%82%A1%E5%88%A9-%E4%B8%8B%E5%AD%A3%E9%85%8D%E6%81%AF%E5%B0%87%E8%AA%BF%E5%8D%87%E8%87%B3-7-%E5%85%83-%E6%9C%80%E5%BE%8C%E8%B2%B7%E9%80%B2%E6%97%A5-%E8%82%A1%E5%88%A9%E7%99%BC%E6%94%BE%E6%97%A5%E4%B8%80%E8%A1%A8%E6%95%B4%E7%90%86-67593afe22c5e1140c7f9212"
        },
        {
          "name": "CMoney投資網誌",
          "url": "https://cmnews.com.tw/article/newsyoudeservetoknow-15506b35-b2c4-11f0-be1f-95e1992d4ce8"
        }
      ],
      "summary": "台積電於6月11日除息6元，下季(Q3)配息將調升至7元。摩根士丹利估計2026年全球AI芯片年增70%，CoWoS總需求達115萬片。台積電佔Nvidia晶圓購買量59%，成為AI浪潮最大受惠者。",
      "tw_stock_impact": "台積電為台股權重股與配息指標股。配息提升至7元反映公司信心，吸引長期投資人與配息族群。除息後填息機會高，為績優股布局好時機。",
      "investment_insight": "長期配息持續提升，說明公司営収能見度佳。AI需求年增70%保證未來3-5年成長動能。適合存股族與長期投資人於回檔時進場。",
      "title_idea": "台積電配息7元創新高、AI需求暴增70%！存股族必看的「長期複利機會」",
      "local_angle": "台積電是台灣最具國際競爭力的企業，也是台股指數權重股。其配息與成長前景直接影響台灣投資人的資產與投資信心。"
    },
    {
      "title": "AI芯片供應鏈面臨三大瓶頸 台灣成全球關鍵樞紐",
      "sources": [
        {
          "name": "聯合新聞網",
          "url": "https://udn.com/news/story/7251/9097377"
        },
        {
          "name": "大紀元",
          "url": "https://www.epochtimes.com/b5/26/6/9/n14785111.htm"
        }
      ],
      "summary": "台積電董事長魏哲家指出AI瓶頸不只在晶片產能，還包括電力、設備機台與上游材料。美國政府加強對台積電監管，防止AI晶片規避管制流向中國。台積電、日月光、京元電等台灣供應鏈廠商面臨長期訂單確保與定價權提升。",
      "tw_stock_impact": "台灣成為全球AI芯片供應鏈的關鍵瓶頸解決者。台積電、環球晶、京元電、日月光、合積等公司訂單能見度高，業績成長確定性強。",
      "investment_insight": "供應鏈瓶頸 = 定價權。在AI熱潮持續下，供應鏈廠商可持續提高毛利率。布局台灣芯片製造與材料股，享受結構性成長機會。",
      "title_idea": "AI芯片大塞車！電力、產能、設備全面吃緊，台灣供應鏈廠商躺著賺定價權",
      "local_angle": "台灣在全球AI產業鏈中是不可或缺的一環，任何全球芯片投資都會回流到台灣廠商，保障長期需求。"
    },
    {
      "title": "Nvidia發行250億美元債券 科技巨頭搶資金應戰AI軍備競賽",
      "sources": [
        {
          "name": "Bloomberg",
          "url": "https://feeds.bloomberg.com/markets/news.rss"
        }
      ],
      "summary": "Nvidia發行250億美元高級債券，創公司歷史紀錄。同時期微軟、Meta等科技巨頭也相繼融資，以應對AI基礎設施投資熱潮。這反映出科技公司對AI商機的長期信心，以及融資成本依然低廉。",
      "tw_stock_impact": "科技巨頭的融資計畫帶動半導體與設備供應商訂單。台灣廠商作為Nvidia與其他科技公司的供應鏈伙伴，將受惠於下游融資與投資循環。",
      "investment_insight": "當龍頭企業大額融資時，代表產業景氣有持續性。關注台灣供應鏈廠商是否提升財測與訂單預期，作為買進訊號。",
      "title_idea": "Nvidia大舉融資250億美元！科技龍頭搶錢應戰AI軍備競賽，台灣供應鏈贏家名單曝光",
      "local_angle": "台灣企業是Nvidia與其他AI巨頭的核心供應鏈，融資計畫越大，台灣廠商訂單越充足。"
    },
    {
      "title": "SpaceX上市後股價漲20% 太空經濟新時代吸引長期投資人",
      "sources": [
        {
          "name": "Al Jazeera",
          "url": "https://www.aljazeera.com/economy/2026/6/12/spacex-ipo-debuts-in-us-markets-musk-becomes-worlds-first-trillionaire"
        }
      ],
      "summary": "SpaceX上市後第二日股價上漲20%至165美元，反映投資人看好該公司的衛星寬帶(Starlink)、發射服務與AI運算中心等多元業務。IPO籌資將用於擴建發射基礎設施與AI基礎設施，預示未來10年高成長。",
      "tw_stock_impact": "SpaceX上市開啟太空經濟投資新範疇。台灣精密製造、航太零組件供應商(如松翰、義隆、頻寶等)可望成為SpaceX供應鏈的間接受益者。",
      "investment_insight": "太空經濟成為新興成長產業。布局台灣航太與衛星通訊相關廠商，享受長期結構性成長。SpaceX上市也示範了『科技創新企業進入資本市場』的新機會。",
      "title_idea": "SpaceX上市後股價狂漲20%！太空經濟時代來臨，台灣精密製造廠商準備接單爆發",
      "local_angle": "Space X與台灣精密製造的供應鏈關係正式浮上檯面，國際太空競賽成為台灣製造業的新成長引擎。"
    }
  ],
  "macro_observations": [
    {
      "title": "Fed新主席Walsh上任 利率維持不變但政策風向轉變",
      "sources": [
        {
          "name": "豐雲學堂",
          "url": "https://www.sinotrade.com.tw/richclub/hotstock/%E5%8F%B0%E8%82%A1%E6%80%A5%E8%B7%8C%E9%82%84%E6%9C%83%E5%86%8D%E9%9C%87%E5%97%8E-%E6%9C%AA%E4%BE%86%E5%85%A9%E9%80%B1%E9%97%9C%E9%8D%B5%E4%BA%8B%E4%BB%B6%E4%B8%80%E6%AC%A1%E7%9C%8B-%E5%8F%B0%E8%82%A1%E6%80%A5%E8%B7%8C%E9%82%84%E6%9C%83%E5%86%8D%E9%9C%87%E5%97%8E-%E6%9C%AA%E4%BE%86%E5%85%A9%E9%80%B1%E9%97%9C%E9%8D%B5%E4%BA%8B%E4%BB%B6%E4%B8%80%E6%AC%A1%E7%9C%8B-%E5%8F%B0%E7%A9%8D%E9%9B%BB%E9%99%A4%E6%81%AF-%E7%BE%8E%E5%9C%8B-CPI-Fed-%E6%B1%BA%E7%AD%96%E6%88%90%E8%A7%80%E5%AF%9F%E9%87%8D%E9%BB%9F-%E8%82%A1%E5%B8%82%E8%A9%B1%E9%A1%8C-6a26074c6c6d82bf0a9806eb"
        }
      ],
      "summary": "Fed於6月17日召開會議，新主席Walsh正式上任接替Powell。市場預期利率維持在3.50%-3.75%不變，但Walsh任期內將面臨通膨與就業數據考驗。摩根大通警告2026年可能不降息、2027年反轉升息。",
      "tw_stock_impact": "美國利率政策影響全球資金流向。若Fed維持高利率或升息，台灣面臨外資流出與新台幣升值壓力。但高利率環境也有利於台灣出口競爭力。",
      "investment_insight": "未來6-12個月的市場重點是Fed政策意圖。若Walsh傾向鷹派(升息),則股市將承壓；若鴿派(降息),則可能迎來反彈。密切關注非農就業數據與通膨指標。",
      "title_idea": "Walsh正式接班Powell！新Fed主席上任隱藏「升息暗示」，6月決議是下半年股市分水嶺",
      "local_angle": "Fed政策直接影響美元強弱，進而衝擊台幣匯率、台灣出口與股市。投資人應密切追蹤Walsh的政策傾向。"
    },
    {
      "title": "芯片通脹威脅全球經濟 AI運算成本壓力浮現",
      "sources": [
        {
          "name": "大紀元",
          "url": "https://www.epochtimes.com/b5/26/6/4/n14782143.htm"
        }
      ],
      "summary": "摩根士丹利報告指出，人工智能對高頻寬記憶體(HBM)與先進晶片的龐大需求推升芯片價格，可能引發『芯片通脹』。HBM價格已經飆升3倍，成為AI基礎設施投資的隱藏成本。此趨勢已成為宏觀經濟問題，可能抬升整體科技投資成本。",
      "tw_stock_impact": "台灣記憶體與芯片廠商(如SK海力士、南亞、華邦)受惠於價格上揚，但下游廠商成本增加。整體而言，上游供應商受益大於下游。",
      "investment_insight": "芯片通脹是『隱藏的通脹壓力』，可能推遲AI投資回報率的實現。關注AI基礎設施成本變化，評估下游廠商的盈利壓力。",
      "title_idea": "『芯片通脹』暗藏危機！HBM價格飆3倍、AI成本壓力浮現，宏觀經濟受衝擊",
      "local_angle": "台灣是全球芯片重鎮，芯片價格變動直接影響台灣廠商毛利率。投資人應監控HBM與先進晶片的價格趨勢。"
    },
    {
      "title": "全球央行政策分化 台灣面臨匯率與資金流向挑戰",
      "sources": [
        {
          "name": "香港文匯網",
          "url": "https://www.wenweipo.com/a/202603/19/AP69bba238e4b04d7d56d93d60.html"
        }
      ],
      "summary": "瑞銀預估Fed將在2026年下半年開始降息兩次，但摩根大通卻警告2026年不降息、2027年可能升息。全球央行政策出現分化，美國、歐洲、中國等主要經濟體的貨幣政策走向不一致，增加市場不確定性。",
      "tw_stock_impact": "央行政策分化加大匯率波動風險。美元強弱變化直接衝擊新台幣匯率、台灣出口企業獲利與匯兌損益。",
      "investment_insight": "在央行政策分化環境下，投資需更謹慎分散風險。關注匯率市場動向，防範美元升值或貶值帶來的衝擊。貨幣政策的不確定性提高了市場波動性。",
      "title_idea": "央行政策大分化！Fed降息vs升息預期混戰，台幣匯率與資金流向何去何從？",
      "local_angle": "台灣央行面臨美國政策不確定性帶來的壓力。投資人應監控新台幣匯率與央行政策動向，防範巨幅波動。"
    }
  ]
}
